pcmonitor/__init__.py
pcmonitor/pcmonitor.py
pcmonitor-0.0.2.data/scripts/pcmonitor
pcmonitor-0.0.2.dist-info/DESCRIPTION.rst
pcmonitor-0.0.2.dist-info/METADATA
pcmonitor-0.0.2.dist-info/RECORD
pcmonitor-0.0.2.dist-info/WHEEL
pcmonitor-0.0.2.dist-info/metadata.json
pcmonitor-0.0.2.dist-info/top_level.txt
