Metadata-Version: 2.0
Name: pcmonitor
Version: 0.0.2
Summary: HTOP Python package
Home-page: https://github.com/suchbeat/pcmonitor.git
Author: suchbeat
Author-email: s.u.chbeat@gmail.com
License: MIT
Platform: UNKNOWN
Requires-Dist: psutil
